README.rst
setup.py
KayleeVC.egg-info/PKG-INFO
KayleeVC.egg-info/SOURCES.txt
KayleeVC.egg-info/dependency_links.txt
KayleeVC.egg-info/entry_points.txt
KayleeVC.egg-info/requires.txt
KayleeVC.egg-info/top_level.txt
kayleevc/__init__.py
kayleevc/gui.py
kayleevc/kaylee.py
kayleevc/numbers.py
kayleevc/recognizer.py
kayleevc/util.py