Metadata-Version: 1.1
Name: KayleeVC
Version: 0.1.1
Summary: Somewhat fancy voice command recognition software
Home-page: https://github.com/Ratfink/kaylee
Author: Clayton G. Hobbs
Author-email: clay@lakeserv.net
License: GPLv3+
Keywords: voice speech command control
Platform: UNKNOWN
Classifier: Development Status :: 3 - Alpha
Classifier: Environment :: X11 Applications :: GTK
Classifier: Intended Audience :: End Users/Desktop
Classifier: License :: OSI Approved :: GNU General Public License v3 or later (GPLv3+)
Classifier: Operating System :: POSIX :: Linux
Classifier: Programming Language :: Python :: 3 :: Only
Classifier: Programming Language :: Python :: 3.5
Classifier: Topic :: Home Automation
